{
  "youtube_id": "9HKNS2utxHI",
  "title": "APOCALIPSE CONEXÃO PROFÉTICA | PARTE 15 |     #escatologianaveia #arrebatamento #thiagovotz",
  "executive_summary": "Este vídeo, parte 15 da série \"Apocalipse Conexão Profética\" de Thiago Votz, explora a escatologia e o cenário profético dos últimos tempos. Aborda temas cruciais como o Apocalipse, o papel de Israel e Jerusalém, o arrebatamento e o retorno de Jesus, tudo sob uma perspectiva de estudo bíblico aprofundado dos eventos do fim dos tempos.",
  "main_topics": [
    "- Escatologia e o Cenário Profético",
    "- O Livro do Apocalipse e Seus Eventos",
    "- O Papel de Israel e Jerusalém nos Últimos Tempos",
    "- A Colheita de Israel e o Povo Judeu",
    "- O Arrebatamento e o Fim dos Tempos",
    "- A Segunda Vinda de Jesus (Maranata)",
    "- Estudo Bíblico Aprofundado sobre Profecias"
  ],
  "keywords": "Apocalipse, Conexão Profética, Escatologia, Arrebatamento, Fim dos Tempos, Israel, Jerusalém, Jesus, Estudo Bíblico, Thiago Votz",
  "data_processamento": "2026-01-19T17:45:20.575Z"
}